dcd/__init__.py
dcd/bucket/__init__.py
dcd/bucket/thing.py
dcd/bucket/thing_http.py
dcd/bucket/thing_logger.py
dcd/bucket/thing_mqtt.py
dcd/bucket/thing_token.py
dcd/bucket/properties/__init__.py
dcd/bucket/properties/ip_address_property.py
dcd/bucket/properties/property.py
dcd/bucket/properties/video_property.py
dcd/examples/__init__.py
dcd/examples/http_shared_example.py
dcd/examples/media_example.py
dcd/examples/mqtt_example.py
dcd/examples/mqtt_shared_properties_example.py
dcd/examples/token_example.py
dcd_sdk-0.1.30.dist-info/LICENSE
dcd_sdk-0.1.30.dist-info/METADATA
dcd_sdk-0.1.30.dist-info/WHEEL
dcd_sdk-0.1.30.dist-info/top_level.txt
dcd_sdk-0.1.30.dist-info/RECORD
