Metadata-Version: 2.1
Name: dcd-sdk
Version: 0.1.30
Summary: Python SDK for the tools of the Data-Centric Design Lab
Home-page: https://github.com/datacentricdesign/dcd-sdk-python
Author: Data-Centric Design Lab
Author-email: lab@datacentricdesign.org
License: MIT
Classifier: Development Status :: 2 - Pre-Alpha
Classifier: Intended Audience :: Science/Research
Classifier: Environment :: Console
Classifier: Topic :: Software Development :: Build Tools
Classifier: Natural Language :: English
Classifier: License :: OSI Approved :: MIT License
Classifier: Programming Language :: Python :: 3
Classifier: Operating System :: OS Independent
License-File: LICENSE
Requires-Dist: requests
Requires-Dist: pyjwt
Requires-Dist: python-dotenv
Requires-Dist: asyncio
Requires-Dist: paho-mqtt
Requires-Dist: cryptography
